MANIFEST.in
README.txt
setup.py
pymadlib/__init__.py
pymadlib/example.py
pymadlib/pymadlib.py
pymadlib/pyroc.py
pymadlib/time_test.py
pymadlib/utils.py
pymadlib.egg-info/PKG-INFO
pymadlib.egg-info/SOURCES.txt
pymadlib.egg-info/dependency_links.txt
pymadlib.egg-info/requires.txt
pymadlib.egg-info/top_level.txt
pymadlib/data/auto_mpg_bool_test.sql
pymadlib/data/auto_mpg_bool_train.sql
pymadlib/data/auto_mpg_test.sql
pymadlib/data/auto_mpg_train.sql
pymadlib/data/debate_lda_dict.sql
pymadlib/data/debate_obama_tokens_temp.sql
pymadlib/data/wine_bool_svm_train_set.sql
pymadlib/data/wine_bool_training_set.sql
pymadlib/data/wine_test_set.sql
pymadlib/data/wine_training_set.sql