Metadata-Version: 1.0
Name: pymadlib
Version: 0.1.2
Summary: A Python wrapper for MADlib (http://madlib.net) - an open source library for scalable in-database machine learning algorithms
Home-page: http://vatsan.github.com/pymadlib
Author: Srivatsan Ramanujam
Author-email: vatsan.cs@utexas.edu
License: LICENSE.txt
Platform: UNKNOWN
